[
  {
    "id": 1,
    "title": "Agendamento de consultas",
    "type": "front-end",
    "img": "",
    "favorite": true,
    "github": "https://github.com/flavio-foa-dev/cliniLagos",
    "site": "https://clini-lagos.vercel.app/",
    "youTube": "https://www.youtube.com/embed/kf2UmO_Azls",
    "tools": "React, react-router-dom, module.css, tailwindcss"
  },
  {
    "id": 2,
    "title": "Sistema pizzaria",
    "type": "front-end",
    "img": "",
    "favorite": true,
    "github": "https://github.com/flavio-foa-dev/pizza",
    "site": "https://pizzaria-kappa.vercel.app/",
    "youTube": "https://www.youtube.com/embed/IrK7_HTw0kg",
    "tools": "React, react-router-dom, module.css,"
  },
  {
    "id": 3,
    "title": "Usando IA",
    "type": "front-end | back-end",
    "img": "",
    "favorite": false,
    "github": "https://github.com/flavio-foa-dev/ia-F",
    "site": "",
    "youTube": "https://www.youtube.com/embed/4sY8CB0rWtE",
    "tools": "Radix UI Open AI ffmpeg wasm Tailwind",
    "motivation": "Plataforma de envio de vídeos",
    "description": "Transcrição, Conversão, Geração de Títulos."
  },
  {
    "id": 4,
    "title": "PortFolio",
    "type": "front-end",
    "img": "",
    "favorite": true,
    "github": "https://github.com/flavio-foa-dev/Portfolio",
    "site": "https://portfolio-di63t7rvi-flavio-foa-dev.vercel.app/",
    "youTube": "https://www.youtube.com/embed/KulCj5hcYSI",
    "tools": "React, react-router-dom, module.css, tailwindcss"
  },
  {
    "id": 5,
    "title": "Ecomerce shoes",
    "type": "front-end",
    "img": "",
    "favorite": true,
    "github": "https://github.com/flavio-foa-dev/ecommerce",
    "site": "https://ecommerce-h2q5.vercel.app/",
    "youTube": "https://www.youtube.com/embed/r6zV25CrscE",
    "tools": "React, Hooks, Custom Hooks, Context, Router, Module.css,"
  },
  {
    "id": 6,
    "title": "Em Breve",
    "type": "front-end",
    "img": "",
    "favorite": false,
    "github": "",
    "site": "",
    "youTube": "",
    "tools": ""
  },
  {
    "id": 7,
    "title": "Em Breve",
    "type": "front-end",
    "img": "",
    "favorite": false,
    "github": "",
    "site": "",
    "youTube": "",
    "tools": ""
  },
  {
    "id": 8,
    "title": "Em Breve",
    "type": "front-end",
    "img": "",
    "favorite": false,
    "github": "",
    "site": "",
    "youTube": "",
    "tools": ""
  }
]